feditest/__init__.py
feditest/disabled.py
feditest/registry.py
feditest/reporting.py
feditest/testplan.py
feditest/testrun.py
feditest/testruncontroller.py
feditest/testruntranscript.py
feditest/tests.py
feditest/utils.py
feditest/cli/__init__.py
feditest/cli/utils.py
feditest/cli/commands/convert_transcript.py
feditest/cli/commands/create_constellation.py
feditest/cli/commands/create_session_template.py
feditest/cli/commands/create_testplan.py
feditest/cli/commands/info.py
feditest/cli/commands/list_nodedrivers.py
feditest/cli/commands/list_tests.py
feditest/cli/commands/run.py
feditest/cli/commands/version.py
feditest/nodedrivers/__init__.py
feditest/nodedrivers/ubos.py
feditest/nodedrivers/fallback/fediverse.py
feditest/nodedrivers/imp/__init__.py
feditest/nodedrivers/manual/__init__.py
feditest/nodedrivers/mastodon/__init__.py
feditest/nodedrivers/mastodon/ubos.py
feditest/nodedrivers/saas/__init__.py
feditest/nodedrivers/sandbox/__init__.py
feditest/nodedrivers/wordpress/__init__.py
feditest/nodedrivers/wordpress/ubos.py
feditest/protocols/__init__.py
feditest/protocols/activitypub/__init__.py
feditest/protocols/activitypub/diag.py
feditest/protocols/activitypub/utils.py
feditest/protocols/fediverse/__init__.py
feditest/protocols/fediverse/diag.py
feditest/protocols/fediverse/utils.py
feditest/protocols/sandbox/__init__.py
feditest/protocols/web/__init__.py
feditest/protocols/web/diag.py
feditest/protocols/webfinger/__init__.py
feditest/protocols/webfinger/abstract.py
feditest/protocols/webfinger/diag.py
feditest/protocols/webfinger/utils.py
feditest/testruntranscriptserializer/__init__.py
feditest/testruntranscriptserializer/html.py
feditest/testruntranscriptserializer/json.py
feditest/testruntranscriptserializer/summary.py
feditest/testruntranscriptserializer/tap.py
feditest/testruntranscriptserializer/templates/testplantranscript_default/matrix.jinja2
feditest/testruntranscriptserializer/templates/testplantranscript_default/session_single.jinja2
feditest-0.5.dist-info/METADATA
feditest-0.5.dist-info/WHEEL
feditest-0.5.dist-info/entry_points.txt
feditest-0.5.dist-info/licenses/LICENSE
feditest-0.5.dist-info/RECORD
